pytholenium/__init__.py
pytholenium/pytholenium.py
pytholenium-1.0.0.dist-info/LICENSE
pytholenium-1.0.0.dist-info/METADATA
pytholenium-1.0.0.dist-info/WHEEL
pytholenium-1.0.0.dist-info/top_level.txt
pytholenium-1.0.0.dist-info/RECORD
