Metadata-Version: 2.1
Name: pytholenium
Version: 1.0.0
Summary: Python-Selenium selector to improve your Automation
Home-page: https://github.com/ArgiesDario/pytholenium
Author: Dario Argies
Author-email: argiesdario@gmail.com
License: UNKNOWN
Platform: UNKNOWN
Classifier: Programming Language :: Python :: 3
Classifier: License :: OSI Approved :: GNU General Public License v3 (GPLv3)
Classifier: Operating System :: OS Independent
Requires-Python: >=3.6
